zinnia_bootstrap4/__init__.py
zinnia_bootstrap4/static/zinnia_bootstrap/assets/ico/apple-touch-icon-114-precomposed.png
zinnia_bootstrap4/static/zinnia_bootstrap/assets/ico/apple-touch-icon-144-precomposed.png
zinnia_bootstrap4/static/zinnia_bootstrap/assets/ico/apple-touch-icon-57-precomposed.png
zinnia_bootstrap4/static/zinnia_bootstrap/assets/ico/apple-touch-icon-72-precomposed.png
zinnia_bootstrap4/static/zinnia_bootstrap/assets/js/html5shiv.js
zinnia_bootstrap4/static/zinnia_bootstrap/assets/js/jquery.js
zinnia_bootstrap4/static/zinnia_bootstrap/assets/js/jquery.slim.min.js
zinnia_bootstrap4/static/zinnia_bootstrap/assets/js/respond.min.js
zinnia_bootstrap4/static/zinnia_bootstrap/bootstrap/version.txt
zinnia_bootstrap4/static/zinnia_bootstrap/bootstrap/css/bootstrap.css
zinnia_bootstrap4/static/zinnia_bootstrap/bootstrap/css/bootstrap.min.css
zinnia_bootstrap4/static/zinnia_bootstrap/bootstrap/fonts/glyphicons-halflings-regular.eot
zinnia_bootstrap4/static/zinnia_bootstrap/bootstrap/fonts/glyphicons-halflings-regular.svg
zinnia_bootstrap4/static/zinnia_bootstrap/bootstrap/fonts/glyphicons-halflings-regular.ttf
zinnia_bootstrap4/static/zinnia_bootstrap/bootstrap/fonts/glyphicons-halflings-regular.woff
zinnia_bootstrap4/static/zinnia_bootstrap/bootstrap/js/bootstrap.js
zinnia_bootstrap4/static/zinnia_bootstrap/bootstrap/js/bootstrap.min.js
zinnia_bootstrap4/static/zinnia_bootstrap/img/zinnia.png
zinnia_bootstrap4/templates/comments/zinnia/entry/form.html
zinnia_bootstrap4/templates/zinnia/_entry_detail_base.html
zinnia_bootstrap4/templates/zinnia/author_list.html
zinnia_bootstrap4/templates/zinnia/base.html
zinnia_bootstrap4/templates/zinnia/category_list.html
zinnia_bootstrap4/templates/zinnia/entry_detail_base.html
zinnia_bootstrap4/templates/zinnia/entry_search.html
zinnia_bootstrap4/templates/zinnia/sitemap.html
zinnia_bootstrap4/templates/zinnia/skeleton.html
zinnia_bootstrap4/templates/zinnia/tag_list.html
zinnia_theme_bootstrap_4-0.6.dist-info/METADATA
zinnia_theme_bootstrap_4-0.6.dist-info/RECORD
zinnia_theme_bootstrap_4-0.6.dist-info/WHEEL
zinnia_theme_bootstrap_4-0.6.dist-info/top_level.txt
