Metadata-Version: 2.1
Name: zinnia-theme-bootstrap-4
Version: 0.6
Summary: Bootstrap 4 theme for django-blog-zinnia
Home-page: https://github.com/sharmi/zinnia-theme-bootstrap-4
Author: Sharmila Gopirajan
Author-email: siva.sharmi@gmail.com
License: BSD License
Keywords: django,blog,weblog,zinnia,theme,skin,bootstrap,bootstrap 4
Platform: UNKNOWN
Classifier: Framework :: Django
Classifier: Development Status :: 5 - Production/Stable
Classifier: Environment :: Web Environment
Classifier: Programming Language :: Python
Classifier: Programming Language :: Python :: 3
Classifier: Intended Audience :: Developers
Classifier: Operating System :: OS Independent
Classifier: License :: OSI Approved :: BSD License
Classifier: Topic :: Software Development :: Libraries :: Python Modules
